websocket/__init__.py
websocket/_abnf.py
websocket/_app.py
websocket/_cookiejar.py
websocket/_core.py
websocket/_exceptions.py
websocket/_handshake.py
websocket/_http.py
websocket/_logging.py
websocket/_socket.py
websocket/_ssl_compat.py
websocket/_url.py
websocket/_utils.py
websocket/tests/__init__.py
websocket/tests/test_abnf.py
websocket/tests/test_app.py
websocket/tests/test_cookiejar.py
websocket/tests/test_http.py
websocket/tests/test_url.py
websocket/tests/test_websocket.py
pyshbullet-1.1.50.dist-info/METADATA
pyshbullet-1.1.50.dist-info/WHEEL
pyshbullet-1.1.50.dist-info/top_level.txt
pyshbullet-1.1.50.dist-info/RECORD
